{
	"name": "Coding in the Sun!",
	"type": "light",
	"colors": {
		// Activity Bar
		"activityBar.background": "#FFF",
		"activityBar.foreground": "#000",
		"activityBar.activeBorder": "#000",
		"activityBar.activeFocusBorder": "#000",
		"activityBar.border": "#CCC",
		"activityBar.inactiveForeground": "#CCC",
		"activityBar.activeBackground": "#eee",
		"activityBarBadge.foreground": "#FFF",
        "activityBarBadge.background": "#000",
        // Editor
		"editor.background": "#FFF",
		"editor.foreground": "#000",
        "editorLineNumber.foreground": "#CCC",
        "editorCursor.foreground": "#000",
        // Image Border
        "imagePreview.border": "#CCC",
		// Side Bar
		"sideBar.background": "#FFF",
		"sideBar.foreground": "#000",
		"sideBar.border": "#CCC",
		"sideBarTitle.foreground": "#000",
		"sideBarSectionHeader.background": "#eee",
		"sideBarSectionHeader.foreground": "#000",
		"sideBarSectionHeader.border": "#CCC",
        // Status Bar
		"statusBar.background": "#FFF",
		"statusBar.foreground": "#000",
		"statusBar.border": "#CCC",
		"statusBar.noFolderForeground": "#000",
		"statusBar.noFolderBackground": "#FFF",
		"statusBar.noFolderBorder": "#CCC",
	},
	"tokenColors": [
        {
            "scope": [
                "comment",
            ],
            "settings": {
                "foreground": "#BBB"
            }
        },
        {
            "scope": [
                "string"
            ],
            "settings": {
                "foreground": "#888"
            }
        },
        {
            "scope": [
                "entity.name.tag",
                "entity.other.attribute-name.class",
                "entity.other.attribute-name.id",
                "keyword.const",
                "keyword.control",
                "keyword.function",
                "keyword.import",
                "keyword.operator.assignment",
                "keyword.operator.comparison",
                "keyword.operator.decrement",
                "keyword.operator.expression",
                "keyword.operator.increment",
                "keyword.operator.increment-decrement",
                "keyword.operator.logical",
                "keyword.operator.misc",
                "keyword.operator.new",
                "keyword.operator.other",
                "keyword.operator.ternary",
                "keyword.package",
                "keyword.type",
                "keyword.var",
                "markup.heading",
                "storage.type.function",
                "storage.type.import",
                "storage.type.interface",
                "storage.type.js",
                "storage.type.type",
            ],
            "settings": {
                "fontStyle": "bold"
            }
        }
    ]
}
